{
  "marketCap": 146677727232,
  "enterpriseValue": 146338349056,
  "trailingPE": 27.471807,
  "forwardPE": 14.532298,
  "priceToSalesTrailing12Months": 5.44926,
  "priceToBook": -26.018663,
  "enterpriseToRevenue": 5.437,
  "enterpriseToEbitda": 14.475,
  "profitMargins": 0.20076999,
  "operatingMargins": 0.32446,
  "grossMargins": 0.87357,
  "returnOnAssets": 0.20815,
  "revenueGrowth": 0.16,
  "revenuePerShare": 829.44,
  "totalDebt": 19413999616,
  "totalCash": 17202999296,
  "totalCashPerShare": 543.138,
  "earningsGrowth": 0.384,
  "earningsQuarterlyGrowth": 0.337,
  "trailingEps": 165.64,
  "forwardEps": 313.1253,
  "bookValue": -174.891,
  "dividendYield": 0.86,
  "dividendRate": 39.3,
  "payoutRatio": 0.2319,
  "beta": 1.227,
  "52WeekChange": 0.022331953,
  "shortRatio": 2.18,
  "shortPercentOfFloat": 0.025899999,
  "freeCashflow": 6550750208,
  "operatingCashflow": 9409000448,
  "currentRatio": 1.333,
  "quickRatio": 1.259,
  "sector": "Consumer Cyclical",
  "industry": "Travel Services",
  "fullTimeEmployees": 23571
}