{
  "marketCap": 190380539904,
  "enterpriseValue": 196218535936,
  "trailingPE": 29.372654,
  "forwardPE": 17.5474,
  "priceToSalesTrailing12Months": 4.2948146,
  "priceToBook": 3.64981,
  "enterpriseToRevenue": 4.427,
  "enterpriseToEbitda": 16.307,
  "profitMargins": 0.14718,
  "operatingMargins": 0.21616,
  "grossMargins": 0.56664,
  "returnOnAssets": 0.066300005,
  "returnOnEquity": 0.12961,
  "revenueGrowth": 0.044,
  "revenuePerShare": 25.461,
  "totalDebt": 14136000512,
  "debtToEquity": 26.787,
  "totalCash": 8938999808,
  "totalCashPerShare": 5.144,
  "earningsGrowth": -0.809,
  "earningsQuarterlyGrowth": -0.808,
  "trailingEps": 3.73,
  "forwardEps": 6.24366,
  "bookValue": 30.018,
  "dividendYield": 2.3,
  "dividendRate": 2.52,
  "payoutRatio": 0.6344,
  "beta": 0.744,
  "52WeekChange": -0.20238787,
  "shortRatio": 1.27,
  "shortPercentOfFloat": 0.0099,
  "freeCashflow": 6288999936,
  "operatingCashflow": 9566000128,
  "currentRatio": 1.576,
  "quickRatio": 1.023,
  "sector": "Healthcare",
  "industry": "Medical Devices",
  "fullTimeEmployees": 115000
}